qlacref_postcodes/__init__.py
qlacref_postcodes/hashes.sig
qlacref_postcodes/hashes.txt
qlacref_postcodes/postcodes_A.pickle.gz
qlacref_postcodes/postcodes_B.pickle.gz
qlacref_postcodes/postcodes_C.pickle.gz
qlacref_postcodes/postcodes_D.pickle.gz
qlacref_postcodes/postcodes_E.pickle.gz
qlacref_postcodes/postcodes_F.pickle.gz
qlacref_postcodes/postcodes_G.pickle.gz
qlacref_postcodes/postcodes_H.pickle.gz
qlacref_postcodes/postcodes_I.pickle.gz
qlacref_postcodes/postcodes_J.pickle.gz
qlacref_postcodes/postcodes_K.pickle.gz
qlacref_postcodes/postcodes_L.pickle.gz
qlacref_postcodes/postcodes_M.pickle.gz
qlacref_postcodes/postcodes_N.pickle.gz
qlacref_postcodes/postcodes_O.pickle.gz
qlacref_postcodes/postcodes_P.pickle.gz
qlacref_postcodes/postcodes_R.pickle.gz
qlacref_postcodes/postcodes_S.pickle.gz
qlacref_postcodes/postcodes_T.pickle.gz
qlacref_postcodes/postcodes_U.pickle.gz
qlacref_postcodes/postcodes_W.pickle.gz
qlacref_postcodes/postcodes_Y.pickle.gz
qlacref_postcodes/postcodes_Z.pickle.gz
quality_lac_data_ref_postcodes-2021.8.1.dist-info/LICENSE.txt
quality_lac_data_ref_postcodes-2021.8.1.dist-info/WHEEL
quality_lac_data_ref_postcodes-2021.8.1.dist-info/METADATA
quality_lac_data_ref_postcodes-2021.8.1.dist-info/RECORD
